{
  "last_update": "2026-02-23T02:28:48.573Z",
  "total": 10,
  "episodes": [
    {
      "id": "4d8480930",
      "series_id": "249d68f38",
      "series_title": "مسلسل عمارة السعادة",
      "number": 5,
      "title": "مسلسل عمارة السعادة الحلقة 5 الخامسة",
      "image": "https://laroza.store/uploads/thumbs/408ac47a6-1.jpg",
      "season": 1,
      "servers": [
        {
          "name": "سيرفر 1",
          "url": "https://sh.ramadan-series.site/watch.php?id=npYEHqmXe"
        },
        {
          "name": "سيرفر 2",
          "url": "https://qq.okprime.site/embed-mpawkbg7rios.html"
        },
        {
          "name": "سيرفر 3",
          "url": "https://vk.com/video_ext.php?oid=897962571&id=456242095"
        },
        {
          "name": "سيرفر 4",
          "url": "https://rty1.film77.xyz/embed-0fo0rw7pfoay.html"
        },
        {
          "name": "سيرفر 5",
          "url": "https://vidoba.org/embed-otbt96bocwuo.html"
        },
        {
          "name": "سيرفر 6",
          "url": "https://larhu.website/g65gc0s0qynj.html"
        },
        {
          "name": "سيرفر 7",
          "url": "https://mp4plus.org/embed-nsho0fpee57p.html"
        },
        {
          "name": "سيرفر 8",
          "url": "https://anafast.org/embed-5y3kw164q9ud.html"
        },
        {
          "name": "سيرفر 9",
          "url": "https://vidspeed.org/embed-m7v79lcwj1kr.html"
        },
        {
          "name": "سيرفر 10",
          "url": "https://short.icu/BrB96gyHW"
        },
        {
          "name": "سيرفر 11",
          "url": "https://vidmoly.net/embed-n2wcqe8dhnp4.html"
        },
        {
          "name": "سيرفر 12",
          "url": "https://dsvplay.com/e/cpo8ofczw11u"
        },
        {
          "name": "سيرفر 13",
          "url": "https://voe.sx/e/tx1jz6sgbj3x"
        }
      ],
      "extracted_at": "2026-02-23T02:28:39.243Z"
    },
    {
      "id": "95e67a23c",
      "series_id": "94d42abbd",
      "series_title": "مسلسل الخطيفة",
      "number": 5,
      "title": "مسلسل الخطيفة الحلقة 5 الخامسة",
      "image": "https://laroza.store/uploads/thumbs/7a29b3c8b-1.jpg",
      "season": 1,
      "servers": [
        {
          "name": "سيرفر 1",
          "url": "https://qq.okprime.site/embed-ft6ztd5kgqif.html"
        },
        {
          "name": "سيرفر 2",
          "url": "https://vk.com/video_ext.php?oid=889347337&id=456247366"
        },
        {
          "name": "سيرفر 3",
          "url": "https://rty1.film77.xyz/embed-t00oqasdi638.html"
        },
        {
          "name": "سيرفر 4",
          "url": "https://vidoba.org/embed-41t0ps3l23h1.html"
        },
        {
          "name": "سيرفر 5",
          "url": "https://larhu.website/0a8rrx5xth7t.html"
        },
        {
          "name": "سيرفر 6",
          "url": "https://mp4plus.org/embed-gmfk601bq25r.html"
        },
        {
          "name": "سيرفر 7",
          "url": "https://anafast.org/embed-e9plhryf7w34.html"
        },
        {
          "name": "سيرفر 8",
          "url": "https://vidspeed.org/embed-afpl94p34vs9.html"
        },
        {
          "name": "سيرفر 9",
          "url": "https://short.icu/WICGL5qOx"
        },
        {
          "name": "سيرفر 10",
          "url": "https://vidmoly.net/embed-h8983c5ryifs.html"
        },
        {
          "name": "سيرفر 11",
          "url": "https://dsvplay.com/e/6z6afoetoq6o"
        },
        {
          "name": "سيرفر 12",
          "url": "https://voe.sx/e/v5pgbnarza5n"
        }
      ],
      "extracted_at": "2026-02-23T02:28:33.750Z"
    },
    {
      "id": "33958d7ba",
      "series_id": "79130bbdd",
      "series_title": "مسلسل العمة",
      "number": 6,
      "title": "مسلسل العمة الحلقة 6 السادسة",
      "image": "https://laroza.store/uploads/thumbs/d7f1cff68-1.jpg",
      "season": 1,
      "servers": [
        {
          "name": "سيرفر 1",
          "url": "https://qq.okprime.site/embed-948c5gqeuwtr.html"
        },
        {
          "name": "سيرفر 2",
          "url": "https://vk.com/video_ext.php?oid=889120958&id=456247760"
        },
        {
          "name": "سيرفر 3",
          "url": "https://rty1.film77.xyz/embed-7lkg9tp2uhvn.html"
        },
        {
          "name": "سيرفر 4",
          "url": "https://vidoba.org/embed-wbj6jeho0rkb.html"
        },
        {
          "name": "سيرفر 5",
          "url": "https://larhu.website/dhjzquu3wi15.html"
        },
        {
          "name": "سيرفر 6",
          "url": "https://mp4plus.org/embed-kunppsnqpyfr.html"
        },
        {
          "name": "سيرفر 7",
          "url": "https://anafast.org/embed-yjdg7pukbadb.html"
        },
        {
          "name": "سيرفر 8",
          "url": "https://vidspeed.org/embed-emo4f3f053g8.html"
        },
        {
          "name": "سيرفر 9",
          "url": "https://minochinos.com/embed/p2b3agn7mqz6"
        },
        {
          "name": "سيرفر 10",
          "url": "https://short.icu/GPqnvdpaY"
        },
        {
          "name": "سيرفر 11",
          "url": "https://vidmoly.net/embed-lyqga0rdtwq1.html"
        },
        {
          "name": "سيرفر 12",
          "url": "https://dsvplay.com/e/h81nlgr66prb"
        },
        {
          "name": "سيرفر 13",
          "url": "https://voe.sx/e/xgqlghb3ssee"
        }
      ],
      "extracted_at": "2026-02-23T02:28:29.578Z"
    },
    {
      "id": "df0eaa61d",
      "series_id": "4c571827e",
      "series_title": "مسلسل أمور عائلية",
      "number": 7,
      "title": "مسلسل امور عائلية الحلقة 7 السابعة",
      "image": "https://laroza.store/uploads/thumbs/c8db11c88-1.jpg",
      "season": 1,
      "servers": [
        {
          "name": "سيرفر 1",
          "url": "https://qq.okprime.site/embed-n4txpf4bqvyq.html"
        },
        {
          "name": "سيرفر 2",
          "url": "https://vk.com/video_ext.php?oid=889347337&id=456247369"
        },
        {
          "name": "سيرفر 3",
          "url": "https://rty1.film77.xyz/embed-nvhs4nounasx.html"
        },
        {
          "name": "سيرفر 4",
          "url": "https://larhu.website/wf9gpdm951r7.html"
        },
        {
          "name": "سيرفر 5",
          "url": "https://mp4plus.org/embed-6y9q3v3k2r7l.html"
        },
        {
          "name": "سيرفر 6",
          "url": "https://anafast.org/embed-kxv4s0u5jw44.html"
        },
        {
          "name": "سيرفر 7",
          "url": "https://vidspeed.org/embed-7bx30d6mme93.html"
        },
        {
          "name": "سيرفر 8",
          "url": "https://short.icu/hDJp82up_"
        },
        {
          "name": "سيرفر 9",
          "url": "https://vidmoly.net/embed-yv3tzc1rmfex.html"
        },
        {
          "name": "سيرفر 10",
          "url": "https://dsvplay.com/e/voa6pzr1bhvd"
        },
        {
          "name": "سيرفر 11",
          "url": "https://voe.sx/e/fizqn4ajeg4y"
        }
      ],
      "extracted_at": "2026-02-23T02:28:15.199Z"
    },
    {
      "id": "8d7927fa9",
      "series_id": "a63f460a8",
      "series_title": "مسلسل ليل البنفسج",
      "number": 6,
      "title": "مسلسل ليل البنفسج الحلقة 6 السادسة",
      "image": "https://laroza.store/uploads/thumbs/b9fe44bf2-1.jpg",
      "season": 1,
      "servers": [
        {
          "name": "سيرفر 1",
          "url": "https://qq.okprime.site/embed-x5k5prm7filb.html"
        },
        {
          "name": "سيرفر 2",
          "url": "https://vk.com/video_ext.php?oid=889347337&id=456247374"
        },
        {
          "name": "سيرفر 3",
          "url": "https://rty1.film77.xyz/embed-bxun6zwdkc0t.html"
        },
        {
          "name": "سيرفر 4",
          "url": "https://larhu.website/x9rrehdzi4fv.html"
        },
        {
          "name": "سيرفر 5",
          "url": "https://mp4plus.org/embed-qo0ufd58i37s.html"
        },
        {
          "name": "سيرفر 6",
          "url": "https://anafast.org/embed-xx77ojeph56l.html"
        },
        {
          "name": "سيرفر 7",
          "url": "https://vidspeed.org/embed-daicdi467a52.html"
        },
        {
          "name": "سيرفر 8",
          "url": "https://short.icu/3siUTx5Kt"
        },
        {
          "name": "سيرفر 9",
          "url": "https://vidmoly.net/embed-1zduhwz766l4.html"
        },
        {
          "name": "سيرفر 10",
          "url": "https://dsvplay.com/e/j9urfjw6n7e8"
        },
        {
          "name": "سيرفر 11",
          "url": "https://voe.sx/e/85b4lq5lptvq"
        }
      ],
      "extracted_at": "2026-02-23T02:27:54.871Z"
    },
    {
      "id": "e27cbc6cf",
      "series_id": "a5fd4a91c",
      "series_title": "مسلسل بيت أم ليلة",
      "number": 6,
      "title": "مسلسل بيت ام ليلة الحلقة 6 السادسة",
      "image": "https://laroza.store/uploads/thumbs/d38cee407-1.jpg",
      "season": 1,
      "servers": [
        {
          "name": "سيرفر 1",
          "url": "https://qq.okprime.site/embed-ge0myeihzvlv.html"
        },
        {
          "name": "سيرفر 2",
          "url": "https://vk.com/video_ext.php?oid=889120958&id=456247743"
        },
        {
          "name": "سيرفر 3",
          "url": "https://rty1.film77.xyz/embed-w4m4sxti24bb.html"
        },
        {
          "name": "سيرفر 4",
          "url": "https://vidoba.org/embed-xybg31xjh5ig.html"
        },
        {
          "name": "سيرفر 5",
          "url": "https://larhu.website/noi1me5fgtf8.html"
        },
        {
          "name": "سيرفر 6",
          "url": "https://mp4plus.org/embed-pr3pov724vpj.html"
        },
        {
          "name": "سيرفر 7",
          "url": "https://anafast.org/embed-k4i97vujn70a.html"
        },
        {
          "name": "سيرفر 8",
          "url": "https://vidspeed.org/embed-hhr9q2up4sb9.html"
        },
        {
          "name": "سيرفر 9",
          "url": "https://short.icu/JBLTP4Lam"
        },
        {
          "name": "سيرفر 10",
          "url": "https://vidmoly.net/embed-8owo9u7dc6my.html"
        },
        {
          "name": "سيرفر 11",
          "url": "https://dsvplay.com/e/e612hxuztohv"
        },
        {
          "name": "سيرفر 12",
          "url": "https://voe.sx/e/tbcdfocnn9ru"
        }
      ],
      "extracted_at": "2026-02-23T02:27:41.317Z"
    },
    {
      "id": "0fdcaa3af",
      "series_id": "e92322c5b",
      "series_title": "مسلسل اسمي حسن",
      "number": 6,
      "title": "مسلسل اسمي حسن الحلقة 6 السادسة",
      "image": "https://laroza.store/uploads/thumbs/b3eee322f-1.jpg",
      "season": 1,
      "servers": [
        {
          "name": "سيرفر 1",
          "url": "https://qq.okprime.site/embed-ge1u3anun0wp.html"
        },
        {
          "name": "سيرفر 2",
          "url": "https://vk.com/video_ext.php?oid=889347337&id=456247370"
        },
        {
          "name": "سيرفر 3",
          "url": "https://rty1.film77.xyz/embed-j175ryajq1a0.html"
        },
        {
          "name": "سيرفر 4",
          "url": "https://vidoba.org/embed-wdxfcliy4ujn.html"
        },
        {
          "name": "سيرفر 5",
          "url": "https://larhu.website/37q7yt3bzjlv.html"
        },
        {
          "name": "سيرفر 6",
          "url": "https://mp4plus.org/embed-gfer1rr7btz4.html"
        },
        {
          "name": "سيرفر 7",
          "url": "https://anafast.org/embed-bmkpovh4fjn2.html"
        },
        {
          "name": "سيرفر 8",
          "url": "https://vidspeed.org/embed-j0qpn4w8892o.html"
        },
        {
          "name": "سيرفر 9",
          "url": "https://short.icu/-hys4KgGi"
        },
        {
          "name": "سيرفر 10",
          "url": "https://vidmoly.net/embed-h5y460tf4oi8.html"
        },
        {
          "name": "سيرفر 11",
          "url": "https://dsvplay.com/e/y3ovizgxh663"
        },
        {
          "name": "سيرفر 12",
          "url": "https://voe.sx/e/xk7ew5u6ticd"
        }
      ],
      "extracted_at": "2026-02-23T02:27:35.579Z"
    },
    {
      "id": "4f7bdf10f",
      "series_id": "3d171dc50",
      "series_title": "مسلسل حمدية",
      "number": 6,
      "title": "مسلسل حمدية الحلقة 6 السادسة",
      "image": "https://laroza.store/uploads/thumbs/1d0241458-1.jpg",
      "season": 1,
      "servers": [
        {
          "name": "سيرفر 1",
          "url": "https://sh.ramadan-series.site/watch.php?id=tuySbFCLx"
        },
        {
          "name": "سيرفر 2",
          "url": "https://qq.okprime.site/embed-dudlhhdcjl6k.html"
        },
        {
          "name": "سيرفر 3",
          "url": "https://vk.com/video_ext.php?oid=897962571&id=456242101"
        },
        {
          "name": "سيرفر 4",
          "url": "https://rty1.film77.xyz/embed-h6yixgsrba2f.html"
        },
        {
          "name": "سيرفر 5",
          "url": "https://vidoba.org/embed-1uhpenke4t7x.html"
        },
        {
          "name": "سيرفر 6",
          "url": "https://larhu.website/p1i2nobc2mtz.html"
        },
        {
          "name": "سيرفر 7",
          "url": "https://mp4plus.org/embed-trwi814zuhk5.html"
        },
        {
          "name": "سيرفر 8",
          "url": "https://anafast.org/embed-viszng1xs3nk.html"
        },
        {
          "name": "سيرفر 9",
          "url": "https://vidspeed.org/embed-l6e4rbvvqphh.html"
        },
        {
          "name": "سيرفر 10",
          "url": "https://short.icu/NkwaAHBb0"
        },
        {
          "name": "سيرفر 11",
          "url": "https://vidmoly.net/embed-kkd8ozzfbzb1.html"
        },
        {
          "name": "سيرفر 12",
          "url": "https://dsvplay.com/e/ovwv2jh31m2o"
        },
        {
          "name": "سيرفر 13",
          "url": "https://voe.sx/e/9pzlrke0hhts"
        }
      ],
      "extracted_at": "2026-02-23T02:27:22.717Z"
    },
    {
      "id": "e3c31b949",
      "series_id": "4b0288b20",
      "series_title": "مسلسل كحيلان",
      "number": 7,
      "title": "مسلسل كحيلان الحلقة 7 السابعة",
      "image": "https://laroza.store/uploads/thumbs/e5a15404f-1.jpg",
      "season": 1,
      "servers": [
        {
          "name": "سيرفر 1",
          "url": "https://sh.ramadan-series.site/watch.php?id=UvGTxbFDz"
        },
        {
          "name": "سيرفر 2",
          "url": "https://qq.okprime.site/embed-dcg8xkm5l8y8.html"
        },
        {
          "name": "سيرفر 3",
          "url": "https://vk.com/video_ext.php?oid=897962571&id=456242100"
        },
        {
          "name": "سيرفر 4",
          "url": "https://rty1.film77.xyz/embed-1gmjkn3oav04.html"
        },
        {
          "name": "سيرفر 5",
          "url": "https://vidoba.org/embed-25shcjubj8qa.html"
        },
        {
          "name": "سيرفر 6",
          "url": "https://larhu.website/dqntd9txkvqn.html"
        },
        {
          "name": "سيرفر 7",
          "url": "https://mp4plus.org/embed-jmpnykf4xfje.html"
        },
        {
          "name": "سيرفر 8",
          "url": "https://anafast.org/embed-lefc4wstzi53.html"
        },
        {
          "name": "سيرفر 9",
          "url": "https://vidspeed.org/embed-6lnt5kdldxkd.html"
        },
        {
          "name": "سيرفر 10",
          "url": "https://short.icu/cxk6prcPS"
        },
        {
          "name": "سيرفر 11",
          "url": "https://vidmoly.net/embed-skbznm0vr2sh.html"
        },
        {
          "name": "سيرفر 12",
          "url": "https://dsvplay.com/e/r6uzynxme2sq"
        },
        {
          "name": "سيرفر 13",
          "url": "https://voe.sx/e/rvzneqptcoav"
        }
      ],
      "extracted_at": "2026-02-23T02:27:19.014Z"
    },
    {
      "id": "8ae7fa4e9",
      "series_id": "df84ca7f0",
      "series_title": "مسلسل متاهة",
      "number": 6,
      "title": "مسلسل متاهة الحلقة 6 السادسة",
      "image": "https://laroza.store/uploads/thumbs/6c3a8bdfe-1.jpg",
      "season": 1,
      "servers": [
        {
          "name": "سيرفر 1",
          "url": "https://qq.okprime.site/embed-dohr0mfqs4bc.html"
        },
        {
          "name": "سيرفر 2",
          "url": "https://vk.com/video_ext.php?oid=889347337&id=456247362"
        },
        {
          "name": "سيرفر 3",
          "url": "https://rty1.film77.xyz/embed-kfy8f2vduno5.html"
        },
        {
          "name": "سيرفر 4",
          "url": "https://vidoba.org/embed-k9mv2a3ysrgt.html"
        },
        {
          "name": "سيرفر 5",
          "url": "https://larhu.website/8w32xs2vyetc.html"
        },
        {
          "name": "سيرفر 6",
          "url": "https://mp4plus.org/embed-hvxrnp9owm06.html"
        },
        {
          "name": "سيرفر 7",
          "url": "https://anafast.org/embed-0hfyxftb3kdy.html"
        },
        {
          "name": "سيرفر 8",
          "url": "https://vidspeed.org/embed-nxdkbroyh4cm.html"
        },
        {
          "name": "سيرفر 9",
          "url": "https://short.icu/TkY_hQwSs"
        },
        {
          "name": "سيرفر 10",
          "url": "https://vidmoly.net/embed-alcxl0hxhx5d.html"
        },
        {
          "name": "سيرفر 11",
          "url": "https://dsvplay.com/e/tk7slj4tax0o"
        },
        {
          "name": "سيرفر 12",
          "url": "https://voe.sx/e/olphuecboakx"
        }
      ],
      "extracted_at": "2026-02-23T02:27:09.775Z"
    }
  ]
}